LICENSE
MANIFEST.in
README.md
setup.cfg
setup.py
faircorelsv2/README.md
faircorelsv2/__init__.py
faircorelsv2/_corels.cpp
faircorelsv2/_corels.pyx
faircorelsv2/corels.py
faircorelsv2/metrics.py
faircorelsv2/utils.py
faircorelsv2.egg-info/PKG-INFO
faircorelsv2.egg-info/SOURCES.txt
faircorelsv2.egg-info/dependency_links.txt
faircorelsv2.egg-info/requires.txt
faircorelsv2.egg-info/top_level.txt
faircorelsv2/src/utils.cpp
faircorelsv2/src/utils.hh
faircorelsv2/src/corels/src/alloc.hh
faircorelsv2/src/corels/src/cache.cpp
faircorelsv2/src/corels/src/cache.hh
faircorelsv2/src/corels/src/corels.cpp
faircorelsv2/src/corels/src/filtering_algorithms.cpp
faircorelsv2/src/corels/src/memoisation_utils.hh
faircorelsv2/src/corels/src/milp_pruning_cplex.cpp
faircorelsv2/src/corels/src/mistral_backtrack.cpp
faircorelsv2/src/corels/src/mistral_backtrack.hpp
faircorelsv2/src/corels/src/mistral_constraint.cpp
faircorelsv2/src/corels/src/mistral_constraint.hpp
faircorelsv2/src/corels/src/mistral_global.cpp
faircorelsv2/src/corels/src/mistral_global.hpp
faircorelsv2/src/corels/src/mistral_sat.cpp
faircorelsv2/src/corels/src/mistral_sat.hpp
faircorelsv2/src/corels/src/mistral_search.cpp
faircorelsv2/src/corels/src/mistral_search.hpp
faircorelsv2/src/corels/src/mistral_solver.cpp
faircorelsv2/src/corels/src/mistral_solver.hpp
faircorelsv2/src/corels/src/mistral_structure.cpp
faircorelsv2/src/corels/src/mistral_structure.hpp
faircorelsv2/src/corels/src/mistral_variable.cpp
faircorelsv2/src/corels/src/mistral_variable.hpp
faircorelsv2/src/corels/src/pmap.cpp
faircorelsv2/src/corels/src/pmap.hh
faircorelsv2/src/corels/src/pruning_interfaces.hh
faircorelsv2/src/corels/src/queue.hh
faircorelsv2/src/corels/src/rule.hh
faircorelsv2/src/corels/src/rulelib.cpp
faircorelsv2/src/corels/src/run.cpp
faircorelsv2/src/corels/src/run.hh
faircorelsv2/src/corels/src/utils.cpp
faircorelsv2/src/corels/src/utils.hh