Metadata-Version: 2.1
Name: faircorelsv2
Version: 1.0
Summary: FairCORELSV2, an enhanced version of the FairCORELS algorithm to build fair optimal rule lists
Home-page: https://github.com/ferryjul/fairCORELSV2
Author:  Julien Ferry, Ulrich Aivodji, Sebastien Gambs, Marie-Jose Huguet, Mohamed Siala
Author-email: julienferry12@gmail.com
License: GNU General Public License v3 (GPLv3)
Platform: UNKNOWN
Classifier: Programming Language :: C++
Classifier: License :: OSI Approved :: GNU General Public License v3 (GPLv3)
Classifier: Operating System :: OS Independent
Requires-Python: >=2.7
License-File: LICENSE
